jutsu/__init__.py
jutsu/block_height.py
jutsu/chain_size.py
jutsu/cli.py
jutsu/connect.py
jutsu/exit_func.py
jutsu/halving.py
jutsu/menu.py
jutsu/supply.py
jutsu-0.0.3.dist-info/LICENSE
jutsu-0.0.3.dist-info/METADATA
jutsu-0.0.3.dist-info/WHEEL
jutsu-0.0.3.dist-info/entry_points.txt
jutsu-0.0.3.dist-info/top_level.txt
jutsu-0.0.3.dist-info/RECORD
