Metadata-Version: 2.1
Name: jutsu
Version: 0.0.3
Summary: Independently verify the Bitcoin supply
Home-page: https://github.com/merwane/jutsu
Author: Merwane Drai
Author-email: merwane@6conf.com
License: MIT
Download-URL: https://github.com/merwane/jutsu
Keywords: bitcoin-verification,bitcoin-cli,bitcoin
Platform: UNKNOWN
Classifier: Intended Audience :: Developers
Classifier: License :: OSI Approved :: MIT License
Classifier: Natural Language :: English
Classifier: Operating System :: OS Independent
Classifier: Programming Language :: Python :: 3.6
Classifier: Programming Language :: Python :: 3.7
Classifier: Programming Language :: Python :: 3.8
Requires-Dist: oogway
Requires-Dist: PyInquirer
Requires-Dist: pyfiglet
Requires-Dist: colorama
Requires-Dist: yaspin
